steps/__init__.py
steps/forward.py
steps/metrics.py
steps/mixin.py
steps/subset.py
step_select-0.1.2.dist-info/LICENSE.txt
step_select-0.1.2.dist-info/METADATA
step_select-0.1.2.dist-info/WHEEL
step_select-0.1.2.dist-info/top_level.txt
step_select-0.1.2.dist-info/RECORD
