Metadata-Version: 2.1
Name: step-select
Version: 0.1.2
Summary: A SciKit-Learn style feature selector using best subsets and stepwise regression.
Home-page: https://github.com/chris-santiago/steps
Author: Chris Santiago
License: MIT License
Project-URL: Documentation, https://chris-santiago.github.io/steps/
Requires-Python: >=3.7
License-File: LICENSE.txt
Requires-Dist: numpy >=1.17.3
Requires-Dist: scikit-learn >=0.23.1
Provides-Extra: build
Requires-Dist: twine ; extra == 'build'
Requires-Dist: wheel ; extra == 'build'
Provides-Extra: docs
Requires-Dist: sphinx ; extra == 'docs'
Requires-Dist: furo ; extra == 'docs'
Requires-Dist: myst-parser ; extra == 'docs'
Provides-Extra: qa
Requires-Dist: mypy ; extra == 'qa'
Requires-Dist: pylint ; extra == 'qa'
Requires-Dist: flake8 ; extra == 'qa'
Requires-Dist: isort ; extra == 'qa'
Requires-Dist: check-manifest ; extra == 'qa'
Requires-Dist: pre-commit ; extra == 'qa'
Provides-Extra: tests
Requires-Dist: nox ; extra == 'tests'
Requires-Dist: pytest ; extra == 'tests'
Requires-Dist: pytest-cov ; extra == 'tests'
Requires-Dist: pandas ; extra == 'tests'
